benchmarks/README.md
benchmarks/__init__.py
benchmarks/datetime_from_database.py
benchmarks/entity_class_mapping_import_row.py
benchmarks/from_database_to_dimension_count_with_nested_map_type.py
benchmarks/get_parameter_value_items.py
benchmarks/map_from_database.py
benchmarks/mapped_item_getitem.py
benchmarks/type_for_scalar.py
benchmarks/update_default_value_to_different_value.py
benchmarks/update_default_value_to_same_value.py
benchmarks/utils.py
spinedb_api/__init__.py
spinedb_api/alembic.ini
spinedb_api/arrow_value.py
spinedb_api/compatibility.py
spinedb_api/dataframes.py
spinedb_api/db_mapping.py
spinedb_api/db_mapping_base.py
spinedb_api/db_mapping_commit_mixin.py
spinedb_api/db_mapping_helpers.py
spinedb_api/db_mapping_query_mixin.py
spinedb_api/exception.py
spinedb_api/export_functions.py
spinedb_api/graph_layout_generator.py
spinedb_api/helpers.py
spinedb_api/import_functions.py
spinedb_api/mapped_item_status.py
spinedb_api/mapped_items.py
spinedb_api/mapping.py
spinedb_api/parameter_value.py
spinedb_api/purge.py
spinedb_api/server_client_helpers.py
spinedb_api/spine_db_client.py
spinedb_api/spine_db_server.py
spinedb_api/temp_id.py
spinedb_api/version.py
spinedb_api/alembic/README
spinedb_api/alembic/env.py
spinedb_api/alembic/script.py.mako
spinedb_api/alembic/versions/02581198a2d8_create_entity_class_display_order_tables.py
spinedb_api/alembic/versions/070a0eb89e88_drop_category_tables.py
spinedb_api/alembic/versions/0c7d199ae915_add_list_value_table.py
spinedb_api/alembic/versions/1892adebc00f_create_metadata_tables.py
spinedb_api/alembic/versions/1e4997105288_separate_type_from_value.py
spinedb_api/alembic/versions/39e860a11b05_add_alternatives_and_scenarios.py
spinedb_api/alembic/versions/51fd7b69acf7_add_parameter_tag_and_parameter_value_list.py
spinedb_api/alembic/versions/5385f063bef2_create_superclass_subclass_table.py
spinedb_api/alembic/versions/6b7c994c1c61_drop_object_and_relationship_tables.py
spinedb_api-0.36.2.dist-info/licenses/COPYING
spinedb_api-0.36.2.dist-info/licenses/COPYING.LESSER
spinedb_api-0.36.2.dist-info/METADATA
spinedb_api-0.36.2.dist-info/WHEEL
spinedb_api-0.36.2.dist-info/top_level.txt
spinedb_api-0.36.2.dist-info/RECORD
