Metadata-Version: 2.4
Name: spinedb_api
Version: 0.36.2
Summary: An API to talk to Spine databases.
Author-email: Spine Project consortium <spine_info@vtt.fi>
License: LGPL-3.0-or-later
Project-URL: Repository, https://github.com/spine-tools/Spine-Database-API
Keywords: energy system modelling,workflow,optimisation,database
Classifier: Programming Language :: Python :: 3
Classifier: License :: OSI Approved :: GNU Lesser General Public License v3 (LGPLv3)
Classifier: Operating System :: OS Independent
Requires-Python: >=3.10
License-File: COPYING
License-File: COPYING.LESSER
Requires-Dist: SQLAlchemy<2.1,>=2.0
Requires-Dist: alembic>=1.7
Requires-Dist: frictionless>=5.18
Requires-Dist: python-dateutil>=2.8.1
Requires-Dist: numpy>=1.20.2
Requires-Dist: scipy>=1.7.1
Requires-Dist: openpyxl!=3.1.1,>=3.0.7
Requires-Dist: GDX2py>=2.2.0
Requires-Dist: ijson>=3.1.4
Requires-Dist: chardet>=4.0.0
Requires-Dist: PyMySQL[rsa]>=1.0.2
Requires-Dist: psycopg2-binary
Requires-Dist: pyarrow>=19.0
Requires-Dist: pandas>=2.2.3
Dynamic: license-file
